powersensor_local/__init__.py
powersensor_local/abstract_event_handler.py
powersensor_local/async_event_emitter.py
powersensor_local/devices.py
powersensor_local/event_buffer.py
powersensor_local/events.py
powersensor_local/f.py
powersensor_local/legacy_discovery.py
powersensor_local/plug_api.py
powersensor_local/plug_listener_tcp.py
powersensor_local/plug_listener_udp.py
powersensor_local/plugevents.py
powersensor_local/rawplug.py
powersensor_local/s.py
powersensor_local/virtual_household.py
powersensor_local/xlatemsg.py
powersensor_local-2.1.0.dist-info/METADATA
powersensor_local-2.1.0.dist-info/WHEEL
powersensor_local-2.1.0.dist-info/entry_points.txt
powersensor_local-2.1.0.dist-info/licenses/LICENSE
powersensor_local-2.1.0.dist-info/RECORD
