Metadata-Version: 2.4
Name: powersensor-local
Version: 2.1.0
Summary: Network-local (non-cloud) interface for Powersensor devices
Project-URL: Repository, https://github.com/DiUS/python-powersensor_local.git
Project-URL: Homepage, https://github.com/DiUS/python-powersensor_local
Project-URL: Issues, https://github.com/DiUS/python-powersensor_local/issues
Author-email: Jade Mattsson <jmattsson@dius.com.au>, Lake Bookman <lbookman@dius.com.au>
License-File: LICENSE
Classifier: Intended Audience :: Developers
Classifier: License :: OSI Approved :: MIT License
Classifier: Operating System :: OS Independent
Classifier: Programming Language :: Python :: 3
Classifier: Topic :: Home Automation
Requires-Python: >=3.11
Provides-Extra: docs
Requires-Dist: sphinx-autodoc-typehints>=1.24.0; extra == 'docs'
Requires-Dist: sphinx-rtd-theme>=1.3.0; extra == 'docs'
Requires-Dist: sphinx>=7.0.0; extra == 'docs'
